plugit/__init__.py
plugit/api.py
plugit/params.py
plugit/routes.py
plugit/utils.py
plugit/views.py
plugit-0.2.0rc2.dist-info/DESCRIPTION.rst
plugit-0.2.0rc2.dist-info/METADATA
plugit-0.2.0rc2.dist-info/RECORD
plugit-0.2.0rc2.dist-info/WHEEL
plugit-0.2.0rc2.dist-info/metadata.json
plugit-0.2.0rc2.dist-info/top_level.txt
