Metadata-Version: 2.0
Name: plugit
Version: 0.2.0rc2
Summary: PlugIt is a framework enhancing the portability and integration of web services requiring a user interface.
Home-page: http://github.com/ebu/PlugIt
Author: EBU Technology & Innovation
Author-email: barroco@ebu.ch
License: BSD
Keywords: frontend
Platform: UNKNOWN
Classifier: Programming Language :: Python
Classifier: Development Status :: 4 - Beta
Classifier: Environment :: Web Environment
Classifier: Framework :: Flask
Classifier: Intended Audience :: Developers
Classifier: License :: OSI Approved :: BSD License
Classifier: Operating System :: OS Independent
Classifier: Topic :: Software Development :: Libraries :: Python Modules
Classifier: Topic :: Internet :: WWW/HTTP :: HTTP Servers
